{
  "iteration_id": "iteration_20251021_140203",
  "timestamp": "2025-10-21T14:02:03.136112",
  "overall_status": "REWORK_REQUIRED",
  "success_criteria": {
    "status": "ERROR",
    "message": "Verification failed: 2025-10-21 14:02:03,295 - INFO - \\U0001f50d Starting success criteria verification...\n2025-10-21 14:02:03,296 - INFO - Checking HIPAA compliance...\n2025-10-21 14:02:03,437 - ERROR - Error in _verify_hipaa_compliance: 'charmap' codec can't decode byte 0x8d in position 1040: character maps to <undefined>\n2025-10-21 14:02:03,437 - INFO - Checking HEDIS alignment...\n2025-10-21 14:02:03,454 - ERROR - Error in _verify_hedis_alignment: 'charmap' codec can't decode byte 0x9d in position 1740: character maps to <undefined>\n2025-10-21 14:02:03,454 - INFO - Checking model performance...\n2025-10-21 14:02:03,467 - INFO - Checking code quality...\n2025-10-21 14:02:03,475 - INFO - Checking testing coverage...\n2025-10-21 14:02:03,608 - INFO - Checking documentation...\n2025-10-21 14:02:03,609 - ERROR - Error in _verify_documentation: 'charmap' codec can't decode byte 0x8f in position 643: character maps to <undefined>\n2025-10-21 14:02:03,609 - INFO - Checking security standards...\n2025-10-21 14:02:03,653 - INFO - \\u2705 Success criteria verification complete: FAIL\nTraceback (most recent call last):\n  File \"C:\\Users\\reich\\Projects\\hedis-gsd-prediction-engine\\scripts\\verify-success-criteria.py\", line 704, in <module>\n    main()\n    ~~~~^^\n  File \"C:\\Users\\reich\\Projects\\hedis-gsd-prediction-engine\\scripts\\verify-success-criteria.py\", line 682, in main\n    report = verifier.generate_report()\n  File \"C:\\Users\\reich\\Projects\\hedis-gsd-prediction-engine\\scripts\\verify-success-criteria.py\", line 658, in generate_report\n    report.append(f\"{status_icon} {criterion.replace('_', ' ').title()}: {details['status']} ({details['score']})\")\n                                                                                               ~~~~~~~^^^^^^^^^\nKeyError: 'score'\n",
    "returncode": 1
  },
  "testing_verification": {
    "status": "ERROR",
    "message": "Verification failed: 2025-10-21 14:02:03,835 - INFO - \\U0001f9ea Starting comprehensive testing verification...\n2025-10-21 14:02:03,836 - INFO - Checking test structure...\n2025-10-21 14:02:03,837 - INFO - Checking test coverage...\n2025-10-21 14:02:03,901 - INFO - Checking test quality...\n2025-10-21 14:02:03,906 - INFO - Checking test execution...\n2025-10-21 14:02:04,035 - INFO - Checking test data management...\n2025-10-21 14:02:04,039 - INFO - Checking healthcare-specific tests...\n2025-10-21 14:02:04,043 - INFO - Checking integration tests...\n2025-10-21 14:02:04,048 - INFO - Checking performance tests...\n2025-10-21 14:02:04,054 - INFO - \\u2705 Testing verification complete: FAIL\nTraceback (most recent call last):\n  File \"C:\\Users\\reich\\Projects\\hedis-gsd-prediction-engine\\scripts\\verify-testing.py\", line 653, in <module>\n    main()\n    ~~~~^^\n  File \"C:\\Users\\reich\\Projects\\hedis-gsd-prediction-engine\\scripts\\verify-testing.py\", line 632, in main\n    print(report)\n    ~~~~~^^^^^^^^\n  File \"C:\\Users\\reich\\AppData\\Local\\Programs\\Python\\Python313\\Lib\\encodings\\cp1252.py\", line 19, in encode\n    return codecs.charmap_encode(input,self.errors,encoding_table)[0]\n           ~~~~~~~~~~~~~~~~~~~~~^^^^^^^^^^^^^^^^^^^^^^^^^^^^^^^^^^\nUnicodeEncodeError: 'charmap' codec can't encode character '\\u274c' in position 194: character maps to <undefined>\n",
    "returncode": 1
  },
  "approval_status": "REWORK",
  "rework_required": [],
  "recommendations": [
    "\u274c Iteration REQUIRES REWORK - Fix critical issues before proceeding"
  ]
}